python_mercuryapi_mqtt/__init__.py
python_mercuryapi_mqtt/__main__.py
python_mercuryapi_mqtt-0.0.4.dist-info/METADATA
python_mercuryapi_mqtt-0.0.4.dist-info/WHEEL
python_mercuryapi_mqtt-0.0.4.dist-info/RECORD
