Metadata-Version: 2.1
Name: python_mercuryapi_mqtt
Version: 0.0.4
Summary: Python mercuryapi mqtt driver
Author: AFraczkowski
Requires-Python: >=3.8,<4.0
Classifier: Programming Language :: Python :: 3
Classifier: Programming Language :: Python :: 3.8
Classifier: Programming Language :: Python :: 3.9
Classifier: Programming Language :: Python :: 3.10
Classifier: Programming Language :: Python :: 3.11
Classifier: Programming Language :: Python :: 3.12
Requires-Dist: paho-mqtt (>=2.1.0,<3.0.0)
Requires-Dist: python-mercuryapi (>=0.5.3,<0.6.0)
